[ {
  "productId" : 1,
  "name" : "Serra de Bancada",
  "category" : "Ferramentas",
  "brand" : "FORTGPRO",
  "prestige" : "****",
  "price" : 1800.00,
  "quantity" : 5,
  "freeShipping" : true
}, {
  "productId" : 2,
  "name" : "Furadeira",
  "category" : "Ferramentas",
  "brand" : "Black & Decker",
  "prestige" : "****",
  "price" : 500.00,
  "quantity" : 7,
  "freeShipping" : true
}, {
  "productId" : 3,
  "name" : "Soldadora",
  "category" : "Ferramentas",
  "brand" : "Black & Decker",
  "prestige" : "***",
  "price" : 3500.00,
  "quantity" : 10,
  "freeShipping" : true
}, {
  "productId" : 4,
  "name" : "Chuteira",
  "category" : "Esportes",
  "brand" : "Adidas",
  "prestige" : "*****",
  "price" : 235.00,
  "quantity" : 6,
  "freeShipping" : true
}, {
  "productId" : 5,
  "name" : "Mini Cama elastica",
  "category" : "Esportes",
  "brand" : "Starboard",
  "prestige" : "*****",
  "price" : 183.00,
  "quantity" : 4,
  "freeShipping" : true
}, {
  "productId" : 6,
  "name" : "Camiseta",
  "category" : "Esportes",
  "brand" : "Topper",
  "prestige" : "***",
  "price" : 80.00,
  "quantity" : 2,
  "freeShipping" : false
}, {
  "productId" : 7,
  "name" : "Redmi Note 9",
  "category" : "Celulares",
  "brand" : "Xiaomi",
  "prestige" : "****",
  "price" : 2800.00,
  "quantity" : 15,
  "freeShipping" : true
}, {
  "productId" : 8,
  "name" : "Smartwatch",
  "category" : "Celulares",
  "brand" : "Noga",
  "prestige" : "**",
  "price" : 1200.00,
  "quantity" : 20,
  "freeShipping" : false
}, {
  "productId" : 9,
  "name" : "Camisa",
  "category" : "Roupas",
  "brand" : "Fila",
  "prestige" : "***",
  "price" : 79.00,
  "quantity" : 2,
  "freeShipping" : false
}, {
  "productId" : 10,
  "name" : "Calças",
  "category" : "Roupas",
  "brand" : "Oakley",
  "prestige" : "***",
  "price" : 73.00,
  "quantity" : 6,
  "freeShipping" : false
}, {
  "productId" : 11,
  "name" : "Meias",
  "category" : "Roupas",
  "brand" : "Gonew",
  "prestige" : "*",
  "price" : 10.00,
  "quantity" : 8,
  "freeShipping" : false
}, {
  "productId" : 12,
  "name" : "Shorts",
  "category" : "Roupas",
  "brand" : "Lacoste",
  "prestige" : "***",
  "price" : 275.00,
  "quantity" : 9,
  "freeShipping" : true
} ]